{
  "title": "Real-time Webtask Logs",
  "name": "auth0-extension-realtime-logs",
  "version": "1.3.3",
  "preVersion": "1.3.3",
  "author": "Auth0, Inc",
  "description": "Access real-time webtask logs",
  "type": "application",
  "repository": "https://github.com/auth0/auth0-extension-realtime-logs",
  "docsUrl": "https://auth0.com/docs/extensions/realtime-webtask-logs",
  "logoUrl": "https://cdn.auth0.com/extensions/auth0-extension-realtime-logs/assets/logo.svg",
  "keywords": [
    "auth0",
    "extension",
    "webtask",
    "logs",
    "real-time"
  ]
}
